stactools/geoparquet_items/__init__.py
stactools/geoparquet_items/commands.py
stactools_geoparquet_items-0.4.0.dist-info/LICENSE
stactools_geoparquet_items-0.4.0.dist-info/METADATA
stactools_geoparquet_items-0.4.0.dist-info/WHEEL
stactools_geoparquet_items-0.4.0.dist-info/top_level.txt
stactools_geoparquet_items-0.4.0.dist-info/RECORD
