Metadata-Version: 2.1
Name: stactools-geoparquet-items
Version: 0.4.0
Summary: Uses stac-geoparquet to generate a geoparquet for a list of STAC items
Home-page: https://github.com/stactools-packages/geoparquet-items
Author: Matthias Mohr
Author-email: matthias@mohr.ws
Project-URL: Issues, https://github.com/stactools-packages/geoparquet-items/issues
Keywords: stactools,pystac,catalog,STAC
Classifier: Development Status :: 4 - Beta
Classifier: License :: OSI Approved :: Apache Software License
Classifier: Programming Language :: Python :: 3.8
Classifier: Programming Language :: Python :: 3.9
Classifier: Programming Language :: Python :: 3.10
Classifier: Programming Language :: Python :: 3.11
License-File: LICENSE
Requires-Dist: stactools (>=0.4.0)
Requires-Dist: stac-geoparquet (>=0.3.2)
Requires-Dist: requests (>=2.0.0)
Requires-Dist: pathlib2 (>=2.3.6)
Requires-Dist: pyogrio (>=0.6.0)
Requires-Dist: pyarrow (>=12.0.0)
Requires-Dist: dask (>=2023.5.0)
Requires-Dist: geopandas (>=0.13.2)
Requires-Dist: dask-geopandas (>=0.3.1)
